codeUtils/__base__.py
codeUtils/__init__.py
codeUtils/__pycache__/__init__.cpython-311.pyc
codeUtils/augment/__init__.py
codeUtils/augment/symmetry.py
codeUtils/callback/__init__.py
codeUtils/callback/boxCallback.py
codeUtils/callback/tqdmCallback.py
codeUtils/decorator/__init__.py
codeUtils/decorator/errorDecorator.py
codeUtils/decorator/execTime.py
codeUtils/decorator/registry.py
codeUtils/decorator/__pycache__/__init__.cpython-311.pyc
codeUtils/decorator/__pycache__/errorDecorator.cpython-311.pyc
codeUtils/decorator/__pycache__/execTime.cpython-311.pyc
codeUtils/display/__init__.py
codeUtils/display/histogram.py
codeUtils/display/imgShow.py
codeUtils/imgOperation/__init__.py
codeUtils/imgOperation/splitImg.py
codeUtils/inference/__init__.py
codeUtils/inference/base.py
codeUtils/inference/boxMatch.py
codeUtils/inference/yoloInfer.py
codeUtils/inference/__pycache__/__init__.cpython-311.pyc
codeUtils/inference/__pycache__/base.cpython-311.pyc
codeUtils/labelOperation/__init__.py
codeUtils/labelOperation/annotaion2labelme.py
codeUtils/labelOperation/coco2other.py
codeUtils/labelOperation/converter.py
codeUtils/labelOperation/cutImgFromLabel.py
codeUtils/labelOperation/labelme2other.py
codeUtils/labelOperation/readLabel.py
codeUtils/labelOperation/saveLabel.py
codeUtils/labelOperation/voc2other.py
codeUtils/labelOperation/yolo2other.py
codeUtils/labelOperation/yoloLabelExclude.py
codeUtils/logTools/__init__.py
codeUtils/logTools/logConfig.py
codeUtils/logTools/__pycache__/__init__.cpython-311.pyc
codeUtils/logTools/__pycache__/logConfig.cpython-311.pyc
codeUtils/matchFactory/__init__.py
codeUtils/matchFactory/bboxMatch.py
codeUtils/matchFactory/shapeMatch.py
codeUtils/matchFactory/__pycache__/__init__.cpython-311.pyc
codeUtils/matchFactory/__pycache__/bboxMatch.cpython-311.pyc
codeUtils/matrix/__init__.py
codeUtils/matrix/confusionMatrix.py
codeUtils/matrix/distMatrix.py
codeUtils/matrix/__pycache__/__init__.cpython-311.pyc
elfinCodeUtils-1.1.7.4.dist-info/LICENSE
elfinCodeUtils-1.1.7.4.dist-info/METADATA
elfinCodeUtils-1.1.7.4.dist-info/WHEEL
elfinCodeUtils-1.1.7.4.dist-info/entry_points.txt
elfinCodeUtils-1.1.7.4.dist-info/top_level.txt
elfinCodeUtils-1.1.7.4.dist-info/RECORD
