Metadata-Version: 2.1
Name: elfinCodeUtils
Version: 1.1.7.4
Summary: 常用功能模块快速使用库.
Classifier: Programming Language :: Python :: 3
Classifier: License :: OSI Approved :: Apache Software License
Requires-Python: >=3.10
License-File: LICENSE
Requires-Dist: loguru (>=0.7.2)
Requires-Dist: seaborn (>=0.13.1)
Requires-Dist: matplotlib (>=3.9.1)
Requires-Dist: msgpack (>=1.1.0)
Requires-Dist: pillow (>=8.1.0)
Requires-Dist: opencv-python (>=4.3.0.38)
Requires-Dist: click
Requires-Dist: pyyaml
Requires-Dist: httpx
Requires-Dist: psutil
Requires-Dist: BeautifulSoup4
Requires-Dist: tqdm
Requires-Dist: lxml
Requires-Dist: prettytable
Requires-Dist: xlsxwriter
